{
  "dependencies": [
    "Miners Delight"
  ],
  "tasks": {
    "sticky": {
      "type": "heracles:item",
      "item": "miners_delight:sticky_basket",
      "amount": 1,
      "collection": "AUTOMATIC",
      "title": "",
      "icon": {
        "item": {
          "id": "miners_delight:sticky_basket",
          "count": 1
        },
        "type": "heracles:item"
      }
    }
  },
  "rewards": {
    "xp": {
      "icon": {
        "item": {
          "id": "minecraft:air",
          "count": 0
        },
        "type": "heracles:item"
      },
      "xptype": "POINTS",
      "amount": 10,
      "title": "",
      "type": "heracles:xp"
    },
    "slime": {
      "title": "",
      "icon": {
        "item": {
          "id": "minecraft:slime_block",
          "count": 1
        },
        "type": "heracles:item"
      },
      "item": {
        "id": "minecraft:slime_block",
        "count": 1
      },
      "type": "heracles:item"
    }
  },
  "display": {
    "subtitle": {
      "text": ""
    },
    "description": [
      "Similar to the Farmers Delight Basket, but objects inside of it can only be removed with hopper-like blocks. Beware this basket it sticky so don't jump into it or you'll get stuck because mods can only jump half a block when inside, waterlogging the basket will prevent this."
    ],
    "groups": {
      "Food": {
        "position": [
          60,
          20
        ]
      }
    },
    "icon": {
      "item": {
        "id": "miners_delight:sticky_basket",
        "count": 1
      },
      "type": "heracles:item"
    },
    "icon_background": "heracles:textures/gui/quest_backgrounds/default.png",
    "title": {
      "translate": "Sticky Backet"
    }
  },
  "settings": {
    "unlockNotification": false,
    "showDependencyArrow": true,
    "repeatable": false,
    "individual_progress": false,
    "hidden": "LOCKED"
  }
}