{
  "dependencies": [
    "Create Addons Page 1"
  ],
  "tasks": {
    "netherite": {
      "type": "heracles:item",
      "item": "minecraft:netherite_ingot",
      "amount": 1,
      "collection": "AUTOMATIC",
      "title": "",
      "icon": {
        "item": {
          "id": "minecraft:air",
          "count": 0
        },
        "type": "heracles:item"
      }
    }
  },
  "rewards": {},
  "display": {
    "subtitle": {
      "text": ""
    },
    "description": [
      "The Void steel ingot is made by heating",
      "a netherite ingot and a ender pearl",
      "in a mixer."
    ],
    "groups": {
      "Create Addons pg 1": {
        "position": [
          100,
          -60
        ]
      }
    },
    "icon": {
      "item": {
        "id": "createutilities:void_steel_ingot",
        "count": 1
      },
      "type": "heracles:item"
    },
    "icon_background": "heracles:textures/gui/quest_backgrounds/octagons.png",
    "title": {
      "translate": "Create Utilities"
    }
  },
  "settings": {
    "unlockNotification": false,
    "showDependencyArrow": false,
    "repeatable": false,
    "individual_progress": false,
    "hidden": "LOCKED"
  }
}