{
  "dependencies": [
    "Create"
  ],
  "tasks": {
    "weight": {
      "type": "heracles:item",
      "item": "create:weighted_ejector",
      "amount": 1,
      "collection": "AUTOMATIC",
      "title": "",
      "icon": {
        "item": {
          "id": "create:weighted_ejector",
          "count": 1
        },
        "type": "heracles:item"
      }
    }
  },
  "rewards": {
    "depot": {
      "title": "",
      "icon": {
        "item": {
          "id": "create:depot",
          "count": 1
        },
        "type": "heracles:item"
      },
      "item": {
        "id": "create:depot",
        "count": 1
      },
      "type": "heracles:item"
    },
    "x": {
      "icon": {
        "item": {
          "id": "minecraft:air",
          "count": 0
        },
        "type": "heracles:item"
      },
      "xptype": "POINTS",
      "amount": 10,
      "title": "",
      "type": "heracles:xp"
    }
  },
  "display": {
    "subtitle": {
      "text": ""
    },
    "description": [
      "Before placing, sneak use the Ejector on a block to target it. The block must be in a straight line from where the Ejector is placed. The further away the target is, the longer the Ejector will take to recharge.",
      "",
      "The amount of items ejected can be adjusted in the Value Settings Screen accessible from either the sides of the block or the top before it has been wound up. The Ejector will wait until it has the appropriate amount of items. The Ejector can also be rotated along with the target block with a Wrench.",
      "",
      "Items flung still have collision, but cannot be picked up or stopped by the player.",
      "",
      "If the Ejector is rotated, the displacement of the target is rotated."
    ],
    "groups": {
      "Create": {
        "position": [
          -40,
          180
        ]
      }
    },
    "icon": {
      "item": {
        "id": "create:weighted_ejector",
        "count": 1
      },
      "type": "heracles:item"
    },
    "icon_background": "heracles:textures/gui/quest_backgrounds/default.png",
    "title": {
      "translate": "Weighted Ejector"
    }
  },
  "settings": {
    "unlockNotification": false,
    "showDependencyArrow": false,
    "repeatable": false,
    "individual_progress": false,
    "hidden": "LOCKED"
  }
}