{
  "dependencies": [
    "Decoration Mods"
  ],
  "tasks": {
    "check": {
      "title": "",
      "icon": {
        "item": {
          "id": "minecraft:air",
          "count": 0
        },
        "type": "heracles:item"
      },
      "type": "heracles:check"
    }
  },
  "rewards": {
    "xp": {
      "icon": {
        "item": {
          "id": "minecraft:air",
          "count": 0
        },
        "type": "heracles:item"
      },
      "xptype": "POINTS",
      "amount": 10,
      "title": "",
      "type": "heracles:xp"
    }
  },
  "display": {
    "subtitle": {
      "text": ""
    },
    "description": [
      "Beautify is a decoration mod that adds tons of blocks that can be used to spruce up your builds, like the following:",
      "- Candelabras",
      "- Blinds",
      "- Lattices",
      "- Picture Frames",
      "- Book Stacks",
      "- Hanging Pots"
    ],
    "groups": {
      "Decoration Mods": {
        "position": [
          0,
          47
        ]
      }
    },
    "icon": {
      "item": {
        "id": "beautify:botanist_workbench",
        "count": 1
      },
      "type": "heracles:item"
    },
    "icon_background": "heracles:textures/gui/quest_backgrounds/default.png",
    "title": {
      "translate": "Beautify"
    }
  },
  "settings": {
    "unlockNotification": false,
    "showDependencyArrow": false,
    "repeatable": false,
    "individual_progress": false,
    "hidden": "LOCKED"
  }
}